{
  "10.1126/science.aba6500": {
    "doi": "10.1126/science.aba6500",
    "title": "Developmental cell programs are co-opted in inflammatory skin disease",
    "authors": "Reynolds G, Vegh P, Fletcher J et al.",
    "journal": "Science",
    "year": 2021,
    "pmid": "33479125",
    "pmcid": "PMC7611557",
    "source": "atlas_source"
  },
  "10.1038/s41586-024-08002-x": {
    "doi": "10.1038/s41586-024-08002-x",
    "title": "A prenatal skin atlas reveals immune regulation of human skin morphogenesis",
    "authors": "Gopee NH et al.",
    "journal": "Nature",
    "year": 2024,
    "source": "atlas_source"
  },
  "10.3389/fsurg.2022.935107": {
    "doi": "10.3389/fsurg.2022.935107",
    "title": "Single-Cell Transcriptional Analysis Deciphers the Inflammatory Response of Skin-Resident Stromal Cells",
    "authors": "Liu B, Li A, Xu J, Cui Y",
    "journal": "Frontiers in Surgery",
    "year": 2022,
    "pmid": "35774389",
    "pmcid": "PMC9237500",
    "source": "citation_traverse"
  }
}