{
  "label": "F1",
  "resolved_names": [
    "fibroblast subset 1",
    "Fb1 fibroblast",
    "dominant dermal fibroblast"
  ],
  "scope": "adult",
  "tissue_context": "adult skin dermis",
  "confidence": "high",
  "evidence": "Reynolds 2021: 'Three fibroblast subsets expressing extracellular matrix (ECM)-related genes such as MMP2, COL1A1, COL1A2 and NT5E (encodes CD73) are present in healthy human skin, dominated by Fb1 fibroblasts with minor populations of Fb2 and Fb3 fibroblasts.' F1 in Gopee 2024 corresponds to Fb1 in Reynolds 2021 — the dominant dermal fibroblast population in healthy skin."
}
